{
  "/directoryObjects": {
    "description": "Provides operations to manage the collection of directoryObject entities.",
    "get": {
      "tags": [
        "directoryObjects.directoryObject"
      ],
      "summary": "Get entities from directoryObjects",
      "operationId": "directoryObjects.directoryObject.ListDirectoryObject",
      "parameters": [
        {
          "either": {
            "Left": {
              "name": "ConsistencyLevel",
              "in": "header",
              "description": "Indicates the requested consistency level. Documentation URL: https://docs.microsoft.com/graph/aad-advanced-queries",
              "required": false,
              "deprecated": false,
              "explode": false,
              "allowReserved": false,
              "schema": {
                "type": "string",
                "readOnly": false,
                "writeOnly": false,
                "required": [],
                "uniqueItems": false,
                "additionalPropertiesAllowed": false,
                "enum": [],
                "nullable": false,
                "deprecated": false,
                "unresolvedReference": false
              },
              "examples": {
                "example-1": {
                  "either": {
                    "Left": {
                      "description": "$search and $count queries require the client to set the ConsistencyLevel HTTP header to 'eventual'.",
                      "value": "eventual"
                    }
                  }
                }
              },
              "content": {}
            }
          }
        },
        {
          "either": {
            "Right": {
              "$ref": "#/components/parameters/top"
            }
          }
        },
        {
          "either": {
            "Right": {
              "$ref": "#/components/parameters/skip"
            }
          }
        },
        {
          "either": {
            "Right": {
              "$ref": "#/components/parameters/search"
            }
          }
        },
        {
          "either": {
            "Right": {
              "$ref": "#/components/parameters/filter"
            }
          }
        },
        {
          "either": {
            "Right": {
              "$ref": "#/components/parameters/count"
            }
          }
        },
        {
          "either": {
            "Left": {
              "name": "$orderby",
              "in": "query",
              "description": "Order items by property values",
              "required": false,
              "deprecated": false,
              "style": "form",
              "explode": false,
              "allowReserved": false,
              "schema": {
                "type": "array",
                "readOnly": false,
                "writeOnly": false,
                "required": [],
                "items": {
                  "type": "string",
                  "readOnly": false,
                  "writeOnly": false,
                  "required": [],
                  "uniqueItems": false,
                  "additionalPropertiesAllowed": false,
                  "enum": [
                    "id",
                    "id desc",
                    "deletedDateTime",
                    "deletedDateTime desc"
                  ],
                  "nullable": false,
                  "deprecated": false,
                  "unresolvedReference": false
                },
                "uniqueItems": true,
                "additionalPropertiesAllowed": false,
                "enum": [],
                "nullable": false,
                "deprecated": false,
                "unresolvedReference": false
              },
              "examples": {},
              "content": {}
            }
          }
        },
        {
          "either": {
            "Left": {
              "name": "$select",
              "in": "query",
              "description": "Select properties to be returned",
              "required": false,
              "deprecated": false,
              "style": "form",
              "explode": false,
              "allowReserved": false,
              "schema": {
                "type": "array",
                "readOnly": false,
                "writeOnly": false,
                "required": [],
                "items": {
                  "type": "string",
                  "readOnly": false,
                  "writeOnly": false,
                  "required": [],
                  "uniqueItems": false,
                  "additionalPropertiesAllowed": false,
                  "enum": [
                    "id",
                    "deletedDateTime"
                  ],
                  "nullable": false,
                  "deprecated": false,
                  "unresolvedReference": false
                },
                "uniqueItems": true,
                "additionalPropertiesAllowed": false,
                "enum": [],
                "nullable": false,
                "deprecated": false,
                "unresolvedReference": false
              },
              "examples": {},
              "content": {}
            }
          }
        },
        {
          "either": {
            "Left": {
              "name": "$expand",
              "in": "query",
              "description": "Expand related entities",
              "required": false,
              "deprecated": false,
              "style": "form",
              "explode": false,
              "allowReserved": false,
              "schema": {
                "type": "array",
                "readOnly": false,
                "writeOnly": false,
                "required": [],
                "items": {
                  "type": "string",
                  "readOnly": false,
                  "writeOnly": false,
                  "required": [],
                  "uniqueItems": false,
                  "additionalPropertiesAllowed": false,
                  "enum": [
                    "*"
                  ],
                  "nullable": false,
                  "deprecated": false,
                  "unresolvedReference": false
                },
                "uniqueItems": true,
                "additionalPropertiesAllowed": false,
                "enum": [],
                "nullable": false,
                "deprecated": false,
                "unresolvedReference": false
              },
              "examples": {},
              "content": {}
            }
          }
        }
      ],
      "responses": {
        "5XX": {
          "either": {
            "Right": {
              "$ref": "#/components/responses/error"
            }
          }
        },
        "4XX": {
          "either": {
            "Right": {
              "$ref": "#/components/responses/error"
            }
          }
        },
        "200": {
          "either": {
            "Right": {
              "$ref": "#/components/responses/microsoft.graph.directoryObjectCollectionResponse"
            }
          }
        }
      },
      "deprecated": false
    },
    "post": {
      "tags": [
        "directoryObjects.directoryObject"
      ],
      "summary": "Add new entity to directoryObjects",
      "operationId": "directoryObjects.directoryObject.CreateDirectoryObject",
      "requestBody": {
        "either": {
          "Left": {
            "description": "New entity",
            "content": {
              "application/json": {
                "schema": {
                  "either": {
                    "Right": {
                      "$ref": "#/components/schemas/microsoft.graph.directoryObject"
                    }
                  }
                }
              }
            },
            "required": true
          }
        }
      },
      "responses": {
        "201": {
          "either": {
            "Left": {
              "description": "Created entity",
              "content": {
                "application/json": {
                  "schema": {
                    "either": {
                      "Right": {
                        "$ref": "#/components/schemas/microsoft.graph.directoryObject"
                      }
                    }
                  }
                }
              }
            }
          }
        },
        "4XX": {
          "either": {
            "Right": {
              "$ref": "#/components/responses/error"
            }
          }
        },
        "5XX": {
          "either": {
            "Right": {
              "$ref": "#/components/responses/error"
            }
          }
        }
      },
      "deprecated": false
    }
  },
  "/directoryObjects/$count": {
    "description": "Provides operations to count the resources in the collection.",
    "get": {
      "summary": "Get the number of the resource",
      "operationId": "Get.Count.directoryObjects-3210",
      "responses": {
        "4XX": {
          "either": {
            "Right": {
              "$ref": "#/components/responses/error"
            }
          }
        },
        "5XX": {
          "either": {
            "Right": {
              "$ref": "#/components/responses/error"
            }
          }
        },
        "200": {
          "either": {
            "Right": {
              "$ref": "#/components/responses/ODataCountResponse"
            }
          }
        }
      },
      "deprecated": false
    }
  },
  "/directoryObjects/microsoft.graph.getAvailableExtensionProperties": {
    "description": "Provides operations to call the getAvailableExtensionProperties method.",
    "post": {
      "tags": [
        "directoryObjects.Actions"
      ],
      "summary": "Invoke action getAvailableExtensionProperties",
      "operationId": "directoryObjects.getAvailableExtensionProperties",
      "requestBody": {
        "either": {
          "Left": {
            "description": "Action parameters",
            "content": {
              "application/json": {
                "schema": {
                  "either": {
                    "Left": {
                      "type": "object",
                      "readOnly": false,
                      "writeOnly": false,
                      "required": [],
                      "uniqueItems": false,
                      "properties": {
                        "isSyncedFromOnPremises": {
                          "type": "boolean",
                          "default": false,
                          "readOnly": false,
                          "writeOnly": false,
                          "required": [],
                          "uniqueItems": false,
                          "additionalPropertiesAllowed": false,
                          "enum": [],
                          "nullable": true,
                          "deprecated": false,
                          "unresolvedReference": false
                        }
                      },
                      "additionalPropertiesAllowed": false,
                      "enum": [],
                      "nullable": false,
                      "deprecated": false,
                      "unresolvedReference": false
                    }
                  }
                }
              }
            },
            "required": true
          }
        }
      },
      "responses": {
        "5XX": {
          "either": {
            "Right": {
              "$ref": "#/components/responses/error"
            }
          }
        },
        "4XX": {
          "either": {
            "Right": {
              "$ref": "#/components/responses/error"
            }
          }
        },
        "200": {
          "either": {
            "Left": {
              "description": "Success",
              "content": {
                "application/json": {
                  "schema": {
                    "either": {
                      "Left": {
                        "title": "Collection of directoryObject",
                        "type": "object",
                        "readOnly": false,
                        "writeOnly": false,
                        "required": [],
                        "uniqueItems": false,
                        "properties": {
                          "value": {
                            "type": "array",
                            "readOnly": false,
                            "writeOnly": false,
                            "required": [],
                            "items": {
                              "readOnly": false,
                              "writeOnly": false,
                              "required": [],
                              "uniqueItems": false,
                              "additionalPropertiesAllowed": false,
                              "enum": [],
                              "nullable": false,
                              "deprecated": false,
                              "unresolvedReference": false,
                              "$ref": "#/components/schemas/microsoft.graph.extensionProperty"
                            },
                            "uniqueItems": false,
                            "additionalPropertiesAllowed": false,
                            "enum": [],
                            "nullable": false,
                            "deprecated": false,
                            "unresolvedReference": false
                          }
                        },
                        "additionalPropertiesAllowed": false,
                        "enum": [],
                        "nullable": false,
                        "deprecated": false,
                        "unresolvedReference": false
                      }
                    }
                  }
                }
              }
            }
          }
        }
      },
      "deprecated": false
    }
  },
  "/directoryObjects/microsoft.graph.getByIds": {
    "description": "Provides operations to call the getByIds method.",
    "post": {
      "tags": [
        "directoryObjects.Actions"
      ],
      "summary": "Invoke action getByIds",
      "operationId": "directoryObjects.getByIds",
      "requestBody": {
        "either": {
          "Left": {
            "description": "Action parameters",
            "content": {
              "application/json": {
                "schema": {
                  "either": {
                    "Left": {
                      "type": "object",
                      "readOnly": false,
                      "writeOnly": false,
                      "required": [],
                      "uniqueItems": false,
                      "properties": {
                        "types": {
                          "type": "array",
                          "readOnly": false,
                          "writeOnly": false,
                          "required": [],
                          "items": {
                            "type": "string",
                            "readOnly": false,
                            "writeOnly": false,
                            "required": [],
                            "uniqueItems": false,
                            "additionalPropertiesAllowed": false,
                            "enum": [],
                            "nullable": true,
                            "deprecated": false,
                            "unresolvedReference": false
                          },
                          "uniqueItems": false,
                          "additionalPropertiesAllowed": false,
                          "enum": [],
                          "nullable": false,
                          "deprecated": false,
                          "unresolvedReference": false
                        },
                        "ids": {
                          "type": "array",
                          "readOnly": false,
                          "writeOnly": false,
                          "required": [],
                          "items": {
                            "type": "string",
                            "readOnly": false,
                            "writeOnly": false,
                            "required": [],
                            "uniqueItems": false,
                            "additionalPropertiesAllowed": false,
                            "enum": [],
                            "nullable": false,
                            "deprecated": false,
                            "unresolvedReference": false
                          },
                          "uniqueItems": false,
                          "additionalPropertiesAllowed": false,
                          "enum": [],
                          "nullable": false,
                          "deprecated": false,
                          "unresolvedReference": false
                        }
                      },
                      "additionalPropertiesAllowed": false,
                      "enum": [],
                      "nullable": false,
                      "deprecated": false,
                      "unresolvedReference": false
                    }
                  }
                }
              }
            },
            "required": true
          }
        }
      },
      "responses": {
        "4XX": {
          "either": {
            "Right": {
              "$ref": "#/components/responses/error"
            }
          }
        },
        "5XX": {
          "either": {
            "Right": {
              "$ref": "#/components/responses/error"
            }
          }
        },
        "200": {
          "either": {
            "Left": {
              "description": "Success",
              "content": {
                "application/json": {
                  "schema": {
                    "either": {
                      "Left": {
                        "title": "Collection of directoryObject",
                        "type": "object",
                        "readOnly": false,
                        "writeOnly": false,
                        "required": [],
                        "uniqueItems": false,
                        "properties": {
                          "value": {
                            "type": "array",
                            "readOnly": false,
                            "writeOnly": false,
                            "required": [],
                            "items": {
                              "readOnly": false,
                              "writeOnly": false,
                              "required": [],
                              "uniqueItems": false,
                              "additionalPropertiesAllowed": false,
                              "enum": [],
                              "nullable": false,
                              "deprecated": false,
                              "unresolvedReference": false,
                              "$ref": "#/components/schemas/microsoft.graph.directoryObject"
                            },
                            "uniqueItems": false,
                            "additionalPropertiesAllowed": false,
                            "enum": [],
                            "nullable": false,
                            "deprecated": false,
                            "unresolvedReference": false
                          }
                        },
                        "additionalPropertiesAllowed": false,
                        "enum": [],
                        "nullable": false,
                        "deprecated": false,
                        "unresolvedReference": false
                      }
                    }
                  }
                }
              }
            }
          }
        }
      },
      "deprecated": false
    }
  },
  "/directoryObjects/microsoft.graph.validateProperties": {
    "description": "Provides operations to call the validateProperties method.",
    "post": {
      "tags": [
        "directoryObjects.Actions"
      ],
      "summary": "Invoke action validateProperties",
      "operationId": "directoryObjects.validateProperties",
      "requestBody": {
        "either": {
          "Left": {
            "description": "Action parameters",
            "content": {
              "application/json": {
                "schema": {
                  "either": {
                    "Left": {
                      "type": "object",
                      "readOnly": false,
                      "writeOnly": false,
                      "required": [],
                      "uniqueItems": false,
                      "properties": {
                        "mailNickname": {
                          "type": "string",
                          "readOnly": false,
                          "writeOnly": false,
                          "required": [],
                          "uniqueItems": false,
                          "additionalPropertiesAllowed": false,
                          "enum": [],
                          "nullable": true,
                          "deprecated": false,
                          "unresolvedReference": false
                        },
                        "onBehalfOfUserId": {
                          "type": "string",
                          "format": "uuid",
                          "pattern": "^[0-9a-fA-F]{8}-[0-9a-fA-F]{4}-[0-9a-fA-F]{4}-[0-9a-fA-F]{4}-[0-9a-fA-F]{12}$",
                          "readOnly": false,
                          "writeOnly": false,
                          "required": [],
                          "uniqueItems": false,
                          "additionalPropertiesAllowed": false,
                          "enum": [],
                          "nullable": true,
                          "deprecated": false,
                          "unresolvedReference": false
                        },
                        "entityType": {
                          "type": "string",
                          "readOnly": false,
                          "writeOnly": false,
                          "required": [],
                          "uniqueItems": false,
                          "additionalPropertiesAllowed": false,
                          "enum": [],
                          "nullable": true,
                          "deprecated": false,
                          "unresolvedReference": false
                        },
                        "displayName": {
                          "type": "string",
                          "readOnly": false,
                          "writeOnly": false,
                          "required": [],
                          "uniqueItems": false,
                          "additionalPropertiesAllowed": false,
                          "enum": [],
                          "nullable": true,
                          "deprecated": false,
                          "unresolvedReference": false
                        }
                      },
                      "additionalPropertiesAllowed": false,
                      "enum": [],
                      "nullable": false,
                      "deprecated": false,
                      "unresolvedReference": false
                    }
                  }
                }
              }
            },
            "required": true
          }
        }
      },
      "responses": {
        "5XX": {
          "either": {
            "Right": {
              "$ref": "#/components/responses/error"
            }
          }
        },
        "204": {
          "either": {
            "Left": {
              "description": "Success"
            }
          }
        },
        "4XX": {
          "either": {
            "Right": {
              "$ref": "#/components/responses/error"
            }
          }
        }
      },
      "deprecated": false
    }
  },
  "/directoryObjects/{directoryObject-id}": {
    "description": "Provides operations to manage the collection of directoryObject entities.",
    "get": {
      "tags": [
        "directoryObjects.directoryObject"
      ],
      "summary": "Get directoryObject",
      "description": "Retrieve the properties and relationships of a directoryObject object.",
      "operationId": "directoryObjects.directoryObject.GetDirectoryObject",
      "parameters": [
        {
          "either": {
            "Left": {
              "name": "$select",
              "in": "query",
              "description": "Select properties to be returned",
              "required": false,
              "deprecated": false,
              "style": "form",
              "explode": false,
              "allowReserved": false,
              "schema": {
                "type": "array",
                "readOnly": false,
                "writeOnly": false,
                "required": [],
                "items": {
                  "type": "string",
                  "readOnly": false,
                  "writeOnly": false,
                  "required": [],
                  "uniqueItems": false,
                  "additionalPropertiesAllowed": false,
                  "enum": [
                    "id",
                    "deletedDateTime"
                  ],
                  "nullable": false,
                  "deprecated": false,
                  "unresolvedReference": false
                },
                "uniqueItems": true,
                "additionalPropertiesAllowed": false,
                "enum": [],
                "nullable": false,
                "deprecated": false,
                "unresolvedReference": false
              },
              "examples": {},
              "content": {}
            }
          }
        },
        {
          "either": {
            "Left": {
              "name": "$expand",
              "in": "query",
              "description": "Expand related entities",
              "required": false,
              "deprecated": false,
              "style": "form",
              "explode": false,
              "allowReserved": false,
              "schema": {
                "type": "array",
                "readOnly": false,
                "writeOnly": false,
                "required": [],
                "items": {
                  "type": "string",
                  "readOnly": false,
                  "writeOnly": false,
                  "required": [],
                  "uniqueItems": false,
                  "additionalPropertiesAllowed": false,
                  "enum": [
                    "*"
                  ],
                  "nullable": false,
                  "deprecated": false,
                  "unresolvedReference": false
                },
                "uniqueItems": true,
                "additionalPropertiesAllowed": false,
                "enum": [],
                "nullable": false,
                "deprecated": false,
                "unresolvedReference": false
              },
              "examples": {},
              "content": {}
            }
          }
        }
      ],
      "responses": {
        "200": {
          "either": {
            "Left": {
              "description": "Retrieved entity",
              "content": {
                "application/json": {
                  "schema": {
                    "either": {
                      "Right": {
                        "$ref": "#/components/schemas/microsoft.graph.directoryObject"
                      }
                    }
                  }
                }
              }
            }
          }
        },
        "5XX": {
          "either": {
            "Right": {
              "$ref": "#/components/responses/error"
            }
          }
        },
        "4XX": {
          "either": {
            "Right": {
              "$ref": "#/components/responses/error"
            }
          }
        }
      },
      "deprecated": false
    },
    "delete": {
      "tags": [
        "directoryObjects.directoryObject"
      ],
      "summary": "Delete directoryObject",
      "description": "Delete a directory object, for example, a group, user, application, or service principal.",
      "operationId": "directoryObjects.directoryObject.DeleteDirectoryObject",
      "parameters": [
        {
          "either": {
            "Left": {
              "name": "If-Match",
              "in": "header",
              "description": "ETag",
              "required": false,
              "deprecated": false,
              "explode": false,
              "allowReserved": false,
              "schema": {
                "type": "string",
                "readOnly": false,
                "writeOnly": false,
                "required": [],
                "uniqueItems": false,
                "additionalPropertiesAllowed": false,
                "enum": [],
                "nullable": false,
                "deprecated": false,
                "unresolvedReference": false
              },
              "examples": {},
              "content": {}
            }
          }
        }
      ],
      "responses": {
        "204": {
          "either": {
            "Left": {
              "description": "Success"
            }
          }
        },
        "4XX": {
          "either": {
            "Right": {
              "$ref": "#/components/responses/error"
            }
          }
        },
        "5XX": {
          "either": {
            "Right": {
              "$ref": "#/components/responses/error"
            }
          }
        }
      },
      "deprecated": false
    },
    "patch": {
      "tags": [
        "directoryObjects.directoryObject"
      ],
      "summary": "Update entity in directoryObjects",
      "operationId": "directoryObjects.directoryObject.UpdateDirectoryObject",
      "requestBody": {
        "either": {
          "Left": {
            "description": "New property values",
            "content": {
              "application/json": {
                "schema": {
                  "either": {
                    "Right": {
                      "$ref": "#/components/schemas/microsoft.graph.directoryObject"
                    }
                  }
                }
              }
            },
            "required": true
          }
        }
      },
      "responses": {
        "4XX": {
          "either": {
            "Right": {
              "$ref": "#/components/responses/error"
            }
          }
        },
        "5XX": {
          "either": {
            "Right": {
              "$ref": "#/components/responses/error"
            }
          }
        },
        "204": {
          "either": {
            "Left": {
              "description": "Success"
            }
          }
        }
      },
      "deprecated": false
    },
    "parameters": [
      {
        "either": {
          "Left": {
            "name": "directoryObject-id",
            "in": "path",
            "description": "key: id of directoryObject",
            "required": true,
            "deprecated": false,
            "explode": false,
            "allowReserved": false,
            "schema": {
              "type": "string",
              "readOnly": false,
              "writeOnly": false,
              "required": [],
              "uniqueItems": false,
              "additionalPropertiesAllowed": false,
              "enum": [],
              "nullable": false,
              "deprecated": false,
              "unresolvedReference": false
            },
            "examples": {},
            "content": {},
            "x-ms-docs-key-type": "directoryObject"
          }
        }
      }
    ]
  },
  "/directoryObjects/{directoryObject-id}/microsoft.graph.checkMemberGroups": {
    "description": "Provides operations to call the checkMemberGroups method.",
    "post": {
      "tags": [
        "directoryObjects.Actions"
      ],
      "summary": "Invoke action checkMemberGroups",
      "operationId": "directoryObjects.directoryObject.checkMemberGroups",
      "requestBody": {
        "either": {
          "Left": {
            "description": "Action parameters",
            "content": {
              "application/json": {
                "schema": {
                  "either": {
                    "Left": {
                      "type": "object",
                      "readOnly": false,
                      "writeOnly": false,
                      "required": [],
                      "uniqueItems": false,
                      "properties": {
                        "groupIds": {
                          "type": "array",
                          "readOnly": false,
                          "writeOnly": false,
                          "required": [],
                          "items": {
                            "type": "string",
                            "readOnly": false,
                            "writeOnly": false,
                            "required": [],
                            "uniqueItems": false,
                            "additionalPropertiesAllowed": false,
                            "enum": [],
                            "nullable": false,
                            "deprecated": false,
                            "unresolvedReference": false
                          },
                          "uniqueItems": false,
                          "additionalPropertiesAllowed": false,
                          "enum": [],
                          "nullable": false,
                          "deprecated": false,
                          "unresolvedReference": false
                        }
                      },
                      "additionalPropertiesAllowed": false,
                      "enum": [],
                      "nullable": false,
                      "deprecated": false,
                      "unresolvedReference": false
                    }
                  }
                }
              }
            },
            "required": true
          }
        }
      },
      "responses": {
        "200": {
          "either": {
            "Left": {
              "description": "Success",
              "content": {
                "application/json": {
                  "schema": {
                    "either": {
                      "Left": {
                        "title": "Collection of directoryObject",
                        "type": "object",
                        "readOnly": false,
                        "writeOnly": false,
                        "required": [],
                        "uniqueItems": false,
                        "properties": {
                          "value": {
                            "type": "array",
                            "readOnly": false,
                            "writeOnly": false,
                            "required": [],
                            "items": {
                              "type": "string",
                              "readOnly": false,
                              "writeOnly": false,
                              "required": [],
                              "uniqueItems": false,
                              "additionalPropertiesAllowed": false,
                              "enum": [],
                              "nullable": false,
                              "deprecated": false,
                              "unresolvedReference": false
                            },
                            "uniqueItems": false,
                            "additionalPropertiesAllowed": false,
                            "enum": [],
                            "nullable": false,
                            "deprecated": false,
                            "unresolvedReference": false
                          }
                        },
                        "additionalPropertiesAllowed": false,
                        "enum": [],
                        "nullable": false,
                        "deprecated": false,
                        "unresolvedReference": false
                      }
                    }
                  }
                }
              }
            }
          }
        },
        "4XX": {
          "either": {
            "Right": {
              "$ref": "#/components/responses/error"
            }
          }
        },
        "5XX": {
          "either": {
            "Right": {
              "$ref": "#/components/responses/error"
            }
          }
        }
      },
      "deprecated": false
    },
    "parameters": [
      {
        "either": {
          "Left": {
            "name": "directoryObject-id",
            "in": "path",
            "description": "key: id of directoryObject",
            "required": true,
            "deprecated": false,
            "explode": false,
            "allowReserved": false,
            "schema": {
              "type": "string",
              "readOnly": false,
              "writeOnly": false,
              "required": [],
              "uniqueItems": false,
              "additionalPropertiesAllowed": false,
              "enum": [],
              "nullable": false,
              "deprecated": false,
              "unresolvedReference": false
            },
            "examples": {},
            "content": {},
            "x-ms-docs-key-type": "directoryObject"
          }
        }
      }
    ]
  },
  "/directoryObjects/{directoryObject-id}/microsoft.graph.checkMemberObjects": {
    "description": "Provides operations to call the checkMemberObjects method.",
    "post": {
      "tags": [
        "directoryObjects.Actions"
      ],
      "summary": "Invoke action checkMemberObjects",
      "operationId": "directoryObjects.directoryObject.checkMemberObjects",
      "requestBody": {
        "either": {
          "Left": {
            "description": "Action parameters",
            "content": {
              "application/json": {
                "schema": {
                  "either": {
                    "Left": {
                      "type": "object",
                      "readOnly": false,
                      "writeOnly": false,
                      "required": [],
                      "uniqueItems": false,
                      "properties": {
                        "ids": {
                          "type": "array",
                          "readOnly": false,
                          "writeOnly": false,
                          "required": [],
                          "items": {
                            "type": "string",
                            "readOnly": false,
                            "writeOnly": false,
                            "required": [],
                            "uniqueItems": false,
                            "additionalPropertiesAllowed": false,
                            "enum": [],
                            "nullable": false,
                            "deprecated": false,
                            "unresolvedReference": false
                          },
                          "uniqueItems": false,
                          "additionalPropertiesAllowed": false,
                          "enum": [],
                          "nullable": false,
                          "deprecated": false,
                          "unresolvedReference": false
                        }
                      },
                      "additionalPropertiesAllowed": false,
                      "enum": [],
                      "nullable": false,
                      "deprecated": false,
                      "unresolvedReference": false
                    }
                  }
                }
              }
            },
            "required": true
          }
        }
      },
      "responses": {
        "4XX": {
          "either": {
            "Right": {
              "$ref": "#/components/responses/error"
            }
          }
        },
        "200": {
          "either": {
            "Left": {
              "description": "Success",
              "content": {
                "application/json": {
                  "schema": {
                    "either": {
                      "Left": {
                        "title": "Collection of directoryObject",
                        "type": "object",
                        "readOnly": false,
                        "writeOnly": false,
                        "required": [],
                        "uniqueItems": false,
                        "properties": {
                          "value": {
                            "type": "array",
                            "readOnly": false,
                            "writeOnly": false,
                            "required": [],
                            "items": {
                              "type": "string",
                              "readOnly": false,
                              "writeOnly": false,
                              "required": [],
                              "uniqueItems": false,
                              "additionalPropertiesAllowed": false,
                              "enum": [],
                              "nullable": false,
                              "deprecated": false,
                              "unresolvedReference": false
                            },
                            "uniqueItems": false,
                            "additionalPropertiesAllowed": false,
                            "enum": [],
                            "nullable": false,
                            "deprecated": false,
                            "unresolvedReference": false
                          }
                        },
                        "additionalPropertiesAllowed": false,
                        "enum": [],
                        "nullable": false,
                        "deprecated": false,
                        "unresolvedReference": false
                      }
                    }
                  }
                }
              }
            }
          }
        },
        "5XX": {
          "either": {
            "Right": {
              "$ref": "#/components/responses/error"
            }
          }
        }
      },
      "deprecated": false
    },
    "parameters": [
      {
        "either": {
          "Left": {
            "name": "directoryObject-id",
            "in": "path",
            "description": "key: id of directoryObject",
            "required": true,
            "deprecated": false,
            "explode": false,
            "allowReserved": false,
            "schema": {
              "type": "string",
              "readOnly": false,
              "writeOnly": false,
              "required": [],
              "uniqueItems": false,
              "additionalPropertiesAllowed": false,
              "enum": [],
              "nullable": false,
              "deprecated": false,
              "unresolvedReference": false
            },
            "examples": {},
            "content": {},
            "x-ms-docs-key-type": "directoryObject"
          }
        }
      }
    ]
  },
  "/directoryObjects/{directoryObject-id}/microsoft.graph.getMemberGroups": {
    "description": "Provides operations to call the getMemberGroups method.",
    "post": {
      "tags": [
        "directoryObjects.Actions"
      ],
      "summary": "Invoke action getMemberGroups",
      "operationId": "directoryObjects.directoryObject.getMemberGroups",
      "requestBody": {
        "either": {
          "Left": {
            "description": "Action parameters",
            "content": {
              "application/json": {
                "schema": {
                  "either": {
                    "Left": {
                      "type": "object",
                      "readOnly": false,
                      "writeOnly": false,
                      "required": [],
                      "uniqueItems": false,
                      "properties": {
                        "securityEnabledOnly": {
                          "type": "boolean",
                          "default": false,
                          "readOnly": false,
                          "writeOnly": false,
                          "required": [],
                          "uniqueItems": false,
                          "additionalPropertiesAllowed": false,
                          "enum": [],
                          "nullable": true,
                          "deprecated": false,
                          "unresolvedReference": false
                        }
                      },
                      "additionalPropertiesAllowed": false,
                      "enum": [],
                      "nullable": false,
                      "deprecated": false,
                      "unresolvedReference": false
                    }
                  }
                }
              }
            },
            "required": true
          }
        }
      },
      "responses": {
        "5XX": {
          "either": {
            "Right": {
              "$ref": "#/components/responses/error"
            }
          }
        },
        "200": {
          "either": {
            "Left": {
              "description": "Success",
              "content": {
                "application/json": {
                  "schema": {
                    "either": {
                      "Left": {
                        "title": "Collection of directoryObject",
                        "type": "object",
                        "readOnly": false,
                        "writeOnly": false,
                        "required": [],
                        "uniqueItems": false,
                        "properties": {
                          "value": {
                            "type": "array",
                            "readOnly": false,
                            "writeOnly": false,
                            "required": [],
                            "items": {
                              "type": "string",
                              "readOnly": false,
                              "writeOnly": false,
                              "required": [],
                              "uniqueItems": false,
                              "additionalPropertiesAllowed": false,
                              "enum": [],
                              "nullable": false,
                              "deprecated": false,
                              "unresolvedReference": false
                            },
                            "uniqueItems": false,
                            "additionalPropertiesAllowed": false,
                            "enum": [],
                            "nullable": false,
                            "deprecated": false,
                            "unresolvedReference": false
                          }
                        },
                        "additionalPropertiesAllowed": false,
                        "enum": [],
                        "nullable": false,
                        "deprecated": false,
                        "unresolvedReference": false
                      }
                    }
                  }
                }
              }
            }
          }
        },
        "4XX": {
          "either": {
            "Right": {
              "$ref": "#/components/responses/error"
            }
          }
        }
      },
      "deprecated": false
    },
    "parameters": [
      {
        "either": {
          "Left": {
            "name": "directoryObject-id",
            "in": "path",
            "description": "key: id of directoryObject",
            "required": true,
            "deprecated": false,
            "explode": false,
            "allowReserved": false,
            "schema": {
              "type": "string",
              "readOnly": false,
              "writeOnly": false,
              "required": [],
              "uniqueItems": false,
              "additionalPropertiesAllowed": false,
              "enum": [],
              "nullable": false,
              "deprecated": false,
              "unresolvedReference": false
            },
            "examples": {},
            "content": {},
            "x-ms-docs-key-type": "directoryObject"
          }
        }
      }
    ]
  },
  "/directoryObjects/{directoryObject-id}/microsoft.graph.getMemberObjects": {
    "description": "Provides operations to call the getMemberObjects method.",
    "post": {
      "tags": [
        "directoryObjects.Actions"
      ],
      "summary": "Invoke action getMemberObjects",
      "operationId": "directoryObjects.directoryObject.getMemberObjects",
      "requestBody": {
        "either": {
          "Left": {
            "description": "Action parameters",
            "content": {
              "application/json": {
                "schema": {
                  "either": {
                    "Left": {
                      "type": "object",
                      "readOnly": false,
                      "writeOnly": false,
                      "required": [],
                      "uniqueItems": false,
                      "properties": {
                        "securityEnabledOnly": {
                          "type": "boolean",
                          "default": false,
                          "readOnly": false,
                          "writeOnly": false,
                          "required": [],
                          "uniqueItems": false,
                          "additionalPropertiesAllowed": false,
                          "enum": [],
                          "nullable": true,
                          "deprecated": false,
                          "unresolvedReference": false
                        }
                      },
                      "additionalPropertiesAllowed": false,
                      "enum": [],
                      "nullable": false,
                      "deprecated": false,
                      "unresolvedReference": false
                    }
                  }
                }
              }
            },
            "required": true
          }
        }
      },
      "responses": {
        "4XX": {
          "either": {
            "Right": {
              "$ref": "#/components/responses/error"
            }
          }
        },
        "200": {
          "either": {
            "Left": {
              "description": "Success",
              "content": {
                "application/json": {
                  "schema": {
                    "either": {
                      "Left": {
                        "title": "Collection of directoryObject",
                        "type": "object",
                        "readOnly": false,
                        "writeOnly": false,
                        "required": [],
                        "uniqueItems": false,
                        "properties": {
                          "value": {
                            "type": "array",
                            "readOnly": false,
                            "writeOnly": false,
                            "required": [],
                            "items": {
                              "type": "string",
                              "readOnly": false,
                              "writeOnly": false,
                              "required": [],
                              "uniqueItems": false,
                              "additionalPropertiesAllowed": false,
                              "enum": [],
                              "nullable": false,
                              "deprecated": false,
                              "unresolvedReference": false
                            },
                            "uniqueItems": false,
                            "additionalPropertiesAllowed": false,
                            "enum": [],
                            "nullable": false,
                            "deprecated": false,
                            "unresolvedReference": false
                          }
                        },
                        "additionalPropertiesAllowed": false,
                        "enum": [],
                        "nullable": false,
                        "deprecated": false,
                        "unresolvedReference": false
                      }
                    }
                  }
                }
              }
            }
          }
        },
        "5XX": {
          "either": {
            "Right": {
              "$ref": "#/components/responses/error"
            }
          }
        }
      },
      "deprecated": false
    },
    "parameters": [
      {
        "either": {
          "Left": {
            "name": "directoryObject-id",
            "in": "path",
            "description": "key: id of directoryObject",
            "required": true,
            "deprecated": false,
            "explode": false,
            "allowReserved": false,
            "schema": {
              "type": "string",
              "readOnly": false,
              "writeOnly": false,
              "required": [],
              "uniqueItems": false,
              "additionalPropertiesAllowed": false,
              "enum": [],
              "nullable": false,
              "deprecated": false,
              "unresolvedReference": false
            },
            "examples": {},
            "content": {},
            "x-ms-docs-key-type": "directoryObject"
          }
        }
      }
    ]
  },
  "/directoryObjects/{directoryObject-id}/microsoft.graph.restore": {
    "description": "Provides operations to call the restore method.",
    "post": {
      "tags": [
        "directoryObjects.Actions"
      ],
      "summary": "Invoke action restore",
      "operationId": "directoryObjects.directoryObject.restore",
      "responses": {
        "200": {
          "either": {
            "Left": {
              "description": "Success",
              "content": {
                "application/json": {
                  "schema": {
                    "either": {
                      "Left": {
                        "readOnly": false,
                        "writeOnly": false,
                        "anyOf": [
                          {
                            "either": {
                              "Right": {
                                "$ref": "#/components/schemas/microsoft.graph.directoryObject"
                              }
                            }
                          },
                          {
                            "either": {
                              "Left": {
                                "type": "object",
                                "readOnly": false,
                                "writeOnly": false,
                                "required": [],
                                "uniqueItems": false,
                                "additionalPropertiesAllowed": false,
                                "enum": [],
                                "nullable": true,
                                "deprecated": false,
                                "unresolvedReference": false
                              }
                            }
                          }
                        ],
                        "required": [],
                        "uniqueItems": false,
                        "additionalPropertiesAllowed": false,
                        "enum": [],
                        "nullable": false,
                        "deprecated": false,
                        "unresolvedReference": false
                      }
                    }
                  }
                }
              }
            }
          }
        },
        "5XX": {
          "either": {
            "Right": {
              "$ref": "#/components/responses/error"
            }
          }
        },
        "4XX": {
          "either": {
            "Right": {
              "$ref": "#/components/responses/error"
            }
          }
        }
      },
      "deprecated": false
    },
    "parameters": [
      {
        "either": {
          "Left": {
            "name": "directoryObject-id",
            "in": "path",
            "description": "key: id of directoryObject",
            "required": true,
            "deprecated": false,
            "explode": false,
            "allowReserved": false,
            "schema": {
              "type": "string",
              "readOnly": false,
              "writeOnly": false,
              "required": [],
              "uniqueItems": false,
              "additionalPropertiesAllowed": false,
              "enum": [],
              "nullable": false,
              "deprecated": false,
              "unresolvedReference": false
            },
            "examples": {},
            "content": {},
            "x-ms-docs-key-type": "directoryObject"
          }
        }
      }
    ]
  }
}