[
  {
    "path": "/instances",
    "param_size": 0,
    "parameters": [],
    "metadata": [
      {
        "has_body": false,
        "request_task": "Json",
        "operation_id": "users.events.ListInstances",
        "operation_mapping": "instances",
        "http_method": "GET",
        "doc": "List instances",
        "parent": "EventsInstances",
        "original_parent": "EventsInstances",
        "resource_identity": "EventsInstances"
      }
    ]
  },
  {
    "path": "/instances/$count",
    "param_size": 0,
    "parameters": [],
    "metadata": [
      {
        "has_body": false,
        "request_task": "Json",
        "operation_id": "Get.Count.instances-f922",
        "operation_mapping": "instances",
        "http_method": "GET",
        "doc": "Get the number of the resource",
        "parent": "EventsInstances",
        "original_parent": "EventsInstances",
        "resource_identity": "EventsInstances"
      }
    ]
  },
  {
    "path": "/instances/delta()",
    "param_size": 0,
    "parameters": [],
    "metadata": [
      {
        "has_body": false,
        "request_task": "Delta",
        "operation_id": "users.user.events.event.instances.delta",
        "operation_mapping": "instances",
        "http_method": "GET",
        "doc": "Invoke function delta",
        "parent": "EventsInstances",
        "original_parent": "EventsInstances",
        "resource_identity": "EventsInstances"
      }
    ]
  },
  {
    "path": "/instances/{{RID}}",
    "param_size": 0,
    "parameters": [],
    "metadata": [
      {
        "has_body": false,
        "request_task": "Json",
        "operation_id": "users.events.GetInstances",
        "operation_mapping": "EventsInstancesId",
        "http_method": "GET",
        "doc": "Get instances from users",
        "parent": "EventsInstancesId",
        "original_parent": "EventsInstances",
        "resource_identity": "EventsInstances"
      }
    ]
  },
  {
    "path": "/instances/{{RID}}/accept",
    "param_size": 0,
    "parameters": [],
    "metadata": [
      {
        "has_body": true,
        "request_task": "NoContent",
        "operation_id": "users.user.events.event.instances.event.accept",
        "operation_mapping": "EventsInstancesId",
        "http_method": "POST",
        "doc": "Invoke action accept",
        "parent": "EventsInstancesId",
        "original_parent": "EventsInstances",
        "resource_identity": "EventsInstances"
      }
    ]
  },
  {
    "path": "/instances/{{RID}}/attachments",
    "param_size": 0,
    "parameters": [],
    "metadata": [
      {
        "has_body": true,
        "request_task": "Json",
        "operation_id": "users.events.instances.CreateAttachments",
        "operation_mapping": "EventsInstancesId",
        "http_method": "POST",
        "doc": "Add attachment",
        "parent": "EventsInstancesId",
        "original_parent": "EventsInstances",
        "resource_identity": "EventsInstances"
      },
      {
        "has_body": false,
        "request_task": "Json",
        "operation_id": "users.events.instances.ListAttachments",
        "operation_mapping": "EventsInstancesId",
        "http_method": "GET",
        "doc": "List attachments",
        "parent": "EventsInstancesId",
        "original_parent": "EventsInstances",
        "resource_identity": "EventsInstances"
      }
    ]
  },
  {
    "path": "/instances/{{RID}}/attachments/$count",
    "param_size": 0,
    "parameters": [],
    "metadata": [
      {
        "has_body": false,
        "request_task": "Json",
        "operation_id": "Get.Count.attachments-3c02",
        "operation_mapping": "EventsInstancesId",
        "http_method": "GET",
        "doc": "Get the number of the resource",
        "parent": "EventsInstancesId",
        "original_parent": "EventsInstances",
        "resource_identity": "EventsInstances"
      }
    ]
  },
  {
    "path": "/instances/{{RID}}/attachments/createUploadSession",
    "param_size": 0,
    "parameters": [],
    "metadata": [
      {
        "has_body": true,
        "request_task": "UploadSession",
        "operation_id": "users.user.events.event.instances.event.attachments.createUploadSession",
        "operation_mapping": "EventsInstancesId",
        "http_method": "POST",
        "doc": "Invoke action createUploadSession",
        "parent": "EventsInstancesId",
        "original_parent": "EventsInstances",
        "resource_identity": "EventsInstances"
      }
    ]
  },
  {
    "path": "/instances/{{RID}}/attachments/{{id}}",
    "param_size": 1,
    "parameters": [
      "attachment_id"
    ],
    "metadata": [
      {
        "has_body": false,
        "request_task": "Json",
        "operation_id": "users.events.instances.GetAttachments",
        "operation_mapping": "EventsInstancesId",
        "http_method": "GET",
        "doc": "Get attachments from users",
        "parent": "EventsInstancesId",
        "original_parent": "EventsInstances",
        "resource_identity": "EventsInstances"
      },
      {
        "has_body": false,
        "request_task": "NoContent",
        "operation_id": "users.events.instances.DeleteAttachments",
        "operation_mapping": "EventsInstancesId",
        "http_method": "DELETE",
        "doc": "Delete navigation property attachments for users",
        "parent": "EventsInstancesId",
        "original_parent": "EventsInstances",
        "resource_identity": "EventsInstances"
      }
    ]
  },
  {
    "path": "/instances/{{RID}}/calendar",
    "param_size": 0,
    "parameters": [],
    "metadata": [
      {
        "has_body": false,
        "request_task": "Json",
        "operation_id": "users.events.instances.GetCalendar",
        "operation_mapping": "EventsInstancesId",
        "http_method": "GET",
        "doc": "Get calendar from users",
        "parent": "EventsInstancesId",
        "original_parent": "EventsInstances",
        "resource_identity": "EventsInstances"
      }
    ]
  },
  {
    "path": "/instances/{{RID}}/cancel",
    "param_size": 0,
    "parameters": [],
    "metadata": [
      {
        "has_body": true,
        "request_task": "NoContent",
        "operation_id": "users.user.events.event.instances.event.cancel",
        "operation_mapping": "EventsInstancesId",
        "http_method": "POST",
        "doc": "Invoke action cancel",
        "parent": "EventsInstancesId",
        "original_parent": "EventsInstances",
        "resource_identity": "EventsInstances"
      }
    ]
  },
  {
    "path": "/instances/{{RID}}/decline",
    "param_size": 0,
    "parameters": [],
    "metadata": [
      {
        "has_body": true,
        "request_task": "NoContent",
        "operation_id": "users.user.events.event.instances.event.decline",
        "operation_mapping": "EventsInstancesId",
        "http_method": "POST",
        "doc": "Invoke action decline",
        "parent": "EventsInstancesId",
        "original_parent": "EventsInstances",
        "resource_identity": "EventsInstances"
      }
    ]
  },
  {
    "path": "/instances/{{RID}}/dismissReminder",
    "param_size": 0,
    "parameters": [],
    "metadata": [
      {
        "has_body": false,
        "request_task": "NoContent",
        "operation_id": "users.user.events.event.instances.event.dismissReminder",
        "operation_mapping": "EventsInstancesId",
        "http_method": "POST",
        "doc": "Invoke action dismissReminder",
        "parent": "EventsInstancesId",
        "original_parent": "EventsInstances",
        "resource_identity": "EventsInstances"
      }
    ]
  },
  {
    "path": "/instances/{{RID}}/extensions",
    "param_size": 0,
    "parameters": [],
    "metadata": [
      {
        "has_body": true,
        "request_task": "Json",
        "operation_id": "users.events.instances.CreateExtensions",
        "operation_mapping": "EventsInstancesId",
        "http_method": "POST",
        "doc": "Create open extension",
        "parent": "EventsInstancesId",
        "original_parent": "EventsInstances",
        "resource_identity": "EventsInstances"
      },
      {
        "has_body": false,
        "request_task": "Json",
        "operation_id": "users.events.instances.ListExtensions",
        "operation_mapping": "EventsInstancesId",
        "http_method": "GET",
        "doc": "Get extensions from users",
        "parent": "EventsInstancesId",
        "original_parent": "EventsInstances",
        "resource_identity": "EventsInstances"
      }
    ]
  },
  {
    "path": "/instances/{{RID}}/extensions/$count",
    "param_size": 0,
    "parameters": [],
    "metadata": [
      {
        "has_body": false,
        "request_task": "Json",
        "operation_id": "Get.Count.extensions-8eed",
        "operation_mapping": "EventsInstancesId",
        "http_method": "GET",
        "doc": "Get the number of the resource",
        "parent": "EventsInstancesId",
        "original_parent": "EventsInstances",
        "resource_identity": "EventsInstances"
      }
    ]
  },
  {
    "path": "/instances/{{RID}}/extensions/{{id}}",
    "param_size": 1,
    "parameters": [
      "extension_id"
    ],
    "metadata": [
      {
        "has_body": false,
        "request_task": "NoContent",
        "operation_id": "users.events.instances.DeleteExtensions",
        "operation_mapping": "EventsInstancesId",
        "http_method": "DELETE",
        "doc": "Delete navigation property extensions for users",
        "parent": "EventsInstancesId",
        "original_parent": "EventsInstances",
        "resource_identity": "EventsInstances"
      },
      {
        "has_body": true,
        "request_task": "Json",
        "operation_id": "users.events.instances.UpdateExtensions",
        "operation_mapping": "EventsInstancesId",
        "http_method": "PATCH",
        "doc": "Update the navigation property extensions in users",
        "parent": "EventsInstancesId",
        "original_parent": "EventsInstances",
        "resource_identity": "EventsInstances"
      },
      {
        "has_body": false,
        "request_task": "Json",
        "operation_id": "users.events.instances.GetExtensions",
        "operation_mapping": "EventsInstancesId",
        "http_method": "GET",
        "doc": "Get extensions from users",
        "parent": "EventsInstancesId",
        "original_parent": "EventsInstances",
        "resource_identity": "EventsInstances"
      }
    ]
  },
  {
    "path": "/instances/{{RID}}/forward",
    "param_size": 0,
    "parameters": [],
    "metadata": [
      {
        "has_body": true,
        "request_task": "NoContent",
        "operation_id": "users.user.events.event.instances.event.forward",
        "operation_mapping": "EventsInstancesId",
        "http_method": "POST",
        "doc": "Invoke action forward",
        "parent": "EventsInstancesId",
        "original_parent": "EventsInstances",
        "resource_identity": "EventsInstances"
      }
    ]
  },
  {
    "path": "/instances/{{RID}}/snoozeReminder",
    "param_size": 0,
    "parameters": [],
    "metadata": [
      {
        "has_body": true,
        "request_task": "NoContent",
        "operation_id": "users.user.events.event.instances.event.snoozeReminder",
        "operation_mapping": "EventsInstancesId",
        "http_method": "POST",
        "doc": "Invoke action snoozeReminder",
        "parent": "EventsInstancesId",
        "original_parent": "EventsInstances",
        "resource_identity": "EventsInstances"
      }
    ]
  },
  {
    "path": "/instances/{{RID}}/tentativelyAccept",
    "param_size": 0,
    "parameters": [],
    "metadata": [
      {
        "has_body": true,
        "request_task": "NoContent",
        "operation_id": "users.user.events.event.instances.event.tentativelyAccept",
        "operation_mapping": "EventsInstancesId",
        "http_method": "POST",
        "doc": "Invoke action tentativelyAccept",
        "parent": "EventsInstancesId",
        "original_parent": "EventsInstances",
        "resource_identity": "EventsInstances"
      }
    ]
  }
]